megrez_collections-0.0.3-py3.6-nspkg.pth
megrez/collections/__init__.py
megrez_collections-0.0.3.dist-info/LICENSE
megrez_collections-0.0.3.dist-info/METADATA
megrez_collections-0.0.3.dist-info/WHEEL
megrez_collections-0.0.3.dist-info/namespace_packages.txt
megrez_collections-0.0.3.dist-info/top_level.txt
megrez_collections-0.0.3.dist-info/RECORD
