Metadata-Version: 2.1
Name: megrez-collections
Version: 0.0.3
Summary: megrez util collections
Home-page: http://gitlab.17zuoye.net/megrez/megrez-collections
Author: megrez
Author-email: megez@z6x.org
License: UNKNOWN
Keywords: megrez,collections
Platform: UNKNOWN
Classifier: Programming Language :: Python :: 3
Classifier: License :: OSI Approved :: MIT License
Classifier: Operating System :: OS Independent
